[
    {
        "id": 1,
        "createdDate": "01/06/2024",
        "email": "john@gmail.com",
        "password": "qwerty",
        "name": "John",
        "lastName": "Doe",
        "authorizedProducts": [
            "101,102"
        ]
    },
    {
        "id": 2,
        "createdDate": "02/06/2024",
        "email": "mary@gmail.com",
        "password": "qwerty",
        "name": "Mary",
        "lastName": "Jane",
        "authorizedProducts": [
            "101,104"
        ]
    },
    {
        "id": 3,
        "createdDate": "03/06/2024",
        "email": "ayse@gmail.com",
        "password": "qwerty",
        "name": "Ayşe",
        "lastName": "Gül",
        "authorizedProducts": [
            "102"
        ]
    },
    {
        "id": 4,
        "createdDate": "04/06/2024",
        "email": "merve@gmail.com",
        "password": "qwerty",
        "name": "Merve",
        "lastName": "Yılmaz",
        "authorizedProducts": [
            "102,103"
        ]
    },
    {
        "id": 5,
        "createdDate": "05/06/2024",
        "email": "sude@gmail.com",
        "password": "qwerty",
        "name": "Sude",
        "lastName": "Ölmez",
        "authorizedProducts": [
            "103,104"
        ]
    },
    {
        "id": 6,
        "createdDate": "06/06/2024",
        "name": "Hatice",
        "email": "hatice@gmail.com",
        "password": "qwerty",
        "lastName": "Yürek",
        "authorizedProducts": [
            "102"
        ]
    },
    {
        "id": 7,
        "createdDate": "07/06/2024",
        "email": "bella@gmail.com",
        "password": "qwerty",
        "name": "Bella",
        "lastName": "Brown",
        "authorizedProducts": [
            "104"
        ]
    }
]